<annotation>
	<folder>images</folder>
	<filename>hard_hat_workers771.png</filename>
	<path>C:\Users\munkhuush\Desktop\helmet_dataset\700-799\images\hard_hat_workers771.png</path>
	<source>
		<database>Unknown</database>
	</source>
	<size>
		<width>415</width>
		<height>416</height>
		<depth>3</depth>
	</size>
	<segmented>0</segmented>
	<object>
		<name>helmet</name>
		<pose>Unspecified</pose>
		<truncated>0</truncated>
		<difficult>0</difficult>
		<bndbox>
			<xmin>208</xmin>
			<ymin>7</ymin>
			<xmax>243</xmax>
			<ymax>47</ymax>
		</bndbox>
	</object>
	<object>
		<name>head_with_helmet</name>
		<pose>Unspecified</pose>
		<truncated>0</truncated>
		<difficult>0</difficult>
		<bndbox>
			<xmin>209</xmin>
			<ymin>7</ymin>
			<xmax>244</xmax>
			<ymax>61</ymax>
		</bndbox>
	</object>
	<object>
		<name>person_with_helmet</name>
		<pose>Unspecified</pose>
		<truncated>0</truncated>
		<difficult>0</difficult>
		<bndbox>
			<xmin>154</xmin>
			<ymin>6</ymin>
			<xmax>304</xmax>
			<ymax>202</ymax>
		</bndbox>
	</object>
</annotation>
